{
  "displayName": "Sidebar",
  "family": "Split column",
  "variantLabel": "Scan rail · PDF",
  "layoutProfile": "sidebar_split",
  "shortDescription": "Left rail: contact, then skills and education in the same order as Organize (sectionOrder). Main: summary, experience, projects. Word still exports classic single-column.",
  "previewImage": "sidebar.png",
  "description": "Rail order for skills vs education follows sectionOrder from the editor (Organize). Main column uses sectionOrder among summary, experience, projects. Education uses build_education_entry_rail in the rail only.",
  "stylingMode": "locked",
  "allowedControls": [],
  "layoutLocked": true,
  "capabilitiesVersion": 1
}
